ysr.cp37-win_amd64.pyd
ysr-2.3.dist-info/METADATA
ysr-2.3.dist-info/WHEEL
ysr-2.3.dist-info/top_level.txt
ysr-2.3.dist-info/RECORD
